nosai/__init__.py
nosai/__main__.py
nosai/numbers.py
numbersai-0.0.1.dist-info/LICENSE
numbersai-0.0.1.dist-info/METADATA
numbersai-0.0.1.dist-info/WHEEL
numbersai-0.0.1.dist-info/entry_points.txt
numbersai-0.0.1.dist-info/top_level.txt
numbersai-0.0.1.dist-info/RECORD
