Metadata-Version: 2.1
Name: numbersai
Version: 0.0.1
Summary: Read numbers like AI
Home-page: https://github.com/kurianbenoy/Reading_like_AI/
Author: Kurian Benoy
Author-email: kurian.bkk@gmail.com
License: MIT
Platform: UNKNOWN
Classifier: License :: OSI Approved :: MIT License
Classifier: Programming Language :: Python :: 3
Classifier: Programming Language :: Python :: 3.7
Requires-Dist: num2words
